server_chat_adub/__init__.py
server_chat_adub/server.py
server_chat_adub/common/__init__.py
server_chat_adub/common/data_transfer.py
server_chat_adub/common/decorators.py
server_chat_adub/common/descriptors.py
server_chat_adub/common/errors.py
server_chat_adub/common/metaclasses.py
server_chat_adub/logs/__init__.py
server_chat_adub/logs/client_log_config.py
server_chat_adub/logs/server_log_config.py
server_chat_adub/server/__init__.py
server_chat_adub/server/add_user.py
server_chat_adub/server/config_window.py
server_chat_adub/server/main_window.py
server_chat_adub/server/remove_user.py
server_chat_adub/server/server_core.py
server_chat_adub/server/server_db.py
server_chat_adub/server/stat_window.py
server_chat_project_adub-0.1.dist-info/METADATA
server_chat_project_adub-0.1.dist-info/WHEEL
server_chat_project_adub-0.1.dist-info/top_level.txt
server_chat_project_adub-0.1.dist-info/RECORD
